docker_app/__init__.py
docker_app/automatization.py
docker_app/nginx_automatization.py
docker_app/workspace.py
lib_docker_app-0.0.8.dist-info/METADATA
lib_docker_app-0.0.8.dist-info/WHEEL
lib_docker_app-0.0.8.dist-info/top_level.txt
lib_docker_app-0.0.8.dist-info/RECORD
