Metadata-Version: 2.1
Name: lib-docker-app
Version: 0.0.8
Summary: Docker app automatization
Author: -
License: MIT
